test_exe_matrix/conftest.py
test_exe_matrix/example_testsuites/matrix.yaml
test_exe_matrix/example_testsuites/very_simple.yaml
test_exe_matrix/main.py
test_exe_matrix/test_data.py
test_exe_matrix/test_the_matrix.py
test_exe_matrix-0.1.5.dist-info/entry_points.txt
test_exe_matrix-0.1.5.dist-info/LICENSE
test_exe_matrix-0.1.5.dist-info/LICENSE_CeCILL_2.1.txt
test_exe_matrix-0.1.5.dist-info/LICENSE_GPL_2.txt
test_exe_matrix-0.1.5.dist-info/WHEEL
test_exe_matrix-0.1.5.dist-info/METADATA
test_exe_matrix-0.1.5.dist-info/RECORD
