Metadata-Version: 2.1
Name: test-exe-matrix
Version: 0.1.5
Summary: Toy project to test executables defined in a yaml file
Home-page: https://framagit.org/feth/test_exe_matrix
Author: Feth AREZKI
Author-email: text_exe_matrix@tuttu.info
Requires-Python: >=3.6
Classifier: Development Status :: 4 - Beta
Classifier: Environment :: Console
Classifier: Framework :: Pytest
Classifier: Intended Audience :: Information Technology
Classifier: Intended Audience :: System Administrators
Classifier: Operating System :: Unix
Classifier: Programming Language :: Python :: 3
Classifier: Programming Language :: Python :: 3.6
Classifier: Programming Language :: Python :: 3.7
Classifier: Programming Language :: Python :: 3.8
Requires-Dist: PyYAML (>=5.2)
Requires-Dist: pytest (==5.3.1)
Project-URL: Bug Tracker, https://framagit.org/feth/test_exe_matrix/issues
Project-URL: Repository, https://framagit.org/feth/test_exe_matrix.git
